[
    {
        "method": "PATCH",
        "path": "/hotels/hotel_id"
    },
    {
        "method": "DELETE",
        "path": "/hotels/hotel_id"
    },
    {
        "method": "POST",
        "path": "/hotels/new"
    },



    {
        "method": "PATCH",
        "path": "/rooms/room_id"
    },
    {
        "method": "DELETE",
        "path": "/rooms/room_id"
    },
    {
        "method": "POST",
        "path": "/rooms/new"
    },



    {
        "method": "PATCH",
        "path": "/users/user_id"
    },
    {
        "method": "DELETE",
        "path": "/rooms/new"
    },


    {
        "method": "GET",
        "path": "/users"
    },
    {
        "method": "GET",
        "path": "/users/user_id"
    },
    {
        "method": "POST",
        "path": "/users/user_id"
    },
    {
        "method": "PATCH",
        "path": "/users/user_id"
    },
    {
        "method": "DELETE",
        "path": "/users/user_id"
    }
]